AuthlyX/__init__.py
AuthlyX/core.py
authlyx-6.3.1.dist-info/METADATA
authlyx-6.3.1.dist-info/WHEEL
authlyx-6.3.1.dist-info/top_level.txt
authlyx-6.3.1.dist-info/RECORD
