Metadata-Version: 2.4
Name: AuthlyX
Version: 6.3.1
Summary: AuthlyX api wrapper
Author: Nonepy
License: MIT
Keywords: auth,authly,authlyx,license
Classifier: Programming Language :: Python :: 3
Classifier: License :: OSI Approved :: MIT License
Classifier: Operating System :: OS Independent
Requires-Python: >=3.8
